openaiexpress/VERSION
openaiexpress/__init__.py
openaiexpress/constant_limits.py
openaiexpress/run.py
openaiexpress/schema/__init__.py
openaiexpress/schema/rate.py
openai_express-0.0.1.dist-info/LICENSE
openai_express-0.0.1.dist-info/METADATA
openai_express-0.0.1.dist-info/WHEEL
openai_express-0.0.1.dist-info/top_level.txt
openai_express-0.0.1.dist-info/RECORD
