Metadata-Version: 2.1
Name: openai-express
Version: 0.0.1
Summary: Max speed OpenAI call. Do not exceed the tpm & rpm limit.
Author-email: vkehfdl1 <vkehfdl1@gmail.com>
License: MIT License
Project-URL: Homepage, https://github.com/vkehfdl1/openai-express
Keywords: openai,parallel
Classifier: Intended Audience :: Developers
Classifier: Intended Audience :: Information Technology
Classifier: Intended Audience :: Science/Research
Classifier: Programming Language :: Python :: 3.8
Classifier: Programming Language :: Python :: 3.9
Classifier: Programming Language :: Python :: 3.10
Classifier: Topic :: Scientific/Engineering :: Artificial Intelligence
Classifier: Topic :: Software Development :: Libraries
Classifier: Topic :: Software Development :: Libraries :: Python Modules
Requires-Python: >=3.8
License-File: LICENSE
Requires-Dist: openai >=1.13.3
Requires-Dist: dataclasses
Requires-Dist: tqdm
Requires-Dist: tiktoken
